{
  "bottlenecks":
  [
    {
      "name":"Global variable"
      , "id":4294967295
      , "src":"1953485776"
      , "dst":"1953486832"
      , "type":"fMAX/II"
      , "brief":"Data dependency"
      , "loop":"conv2d3x3.B11"
      , "details":
      [
        {
          "type":"table"
          , "Variable on critical loop carried feedback path: ":"Global variable"
          , "Declared at: ":
          [
            {
              "type":"text"
              , "text":"%L"
              , "links":
              [
                {
                  "filename":"Unknown location"
                  , "line":"0"
                }
              ]
            }
          ]
          , "Dependency: ":"Data dependency"
          , "Estimated fmax reduced to: ":"240.0"
          , "Loop feedback path that lowered II and Fmax: ":
          [
            {
              "type":"text"
              , "text":"f32 FP *+(%L)"
              , "links":
              [
                {
                  "filename":"/home/joerock/Documents/TFM/Quartus_Sim-Em/Squeezenet/device/v1.3/conv3x3/conv3x3_ST.cl"
                  , "line":"43"
                }
              ]
            }
            , {
              "type":"text"
              , "text":"Select(%L)"
              , "links":
              [
                {
                  "filename":"/home/joerock/Documents/TFM/Quartus_Sim-Em/Squeezenet/device/v1.3/conv3x3/conv3x3_ST.cl"
                  , "line":"43"
                }
              ]
            }
          ]
        }
      ]
      , "nodes":
      [
        {
          "name":"Global variable"
          , "id":1953485776
          , "start":"249.00"
          , "parent":"conv2d3x3.B11"
          , "debug":
          [
            [
              {
                "filename":"/home/joerock/Documents/TFM/Quartus_Sim-Em/Squeezenet/device/v1.3/conv3x3/conv3x3_ST.cl"
                , "line":43
              }
            ]
          ]
          , "type":"inst"
        }
        , {
          "name":"f32 FP *+"
          , "id":1953486128
          , "debug":
          [
            [
              {
                "filename":"/home/joerock/Documents/TFM/Quartus_Sim-Em/Squeezenet/device/v1.3/conv3x3/conv3x3_ST.cl"
                , "line":43
              }
            ]
          ]
          , "type":"inst"
        }
        , {
          "name":"Select"
          , "id":1953486480
          , "debug":
          [
            [
              {
                "filename":"/home/joerock/Documents/TFM/Quartus_Sim-Em/Squeezenet/device/v1.3/conv3x3/conv3x3_ST.cl"
                , "line":43
              }
            ]
          ]
          , "type":"inst"
        }
        , {
          "name":"Feedback"
          , "id":1953486832
          , "end":"253.00"
          , "parent":"conv2d3x3.B11"
          , "debug":
          [
            [
              {
                "filename":"/home/joerock/Documents/TFM/Quartus_Sim-Em/Squeezenet/device/v1.3/conv3x3/conv3x3_ST.cl"
                , "line":43
              }
            ]
          ]
          , "type":"inst"
        }
      ]
      , "links":
      [
        {
          "from":1953485776
          , "to":1953486128
        }
        , {
          "from":1953485776
          , "to":1953486480
        }
        , {
          "from":1953486128
          , "to":1953486480
        }
        , {
          "from":1953486480
          , "to":1953486832
        }
        , {
          "from":1953485776
          , "to":1953486832
          , "reverse":1
        }
      ]
    }
    , {
      "name":"Global variable"
      , "id":4294967295
      , "src":"1953678704"
      , "dst":"1953681168"
      , "type":"fMAX/II"
      , "brief":"Data dependency"
      , "loop":"conv2d3x3.B13"
      , "details":
      [
        {
          "type":"table"
          , "Variable on critical loop carried feedback path: ":"Global variable"
          , "Declared at: ":
          [
            {
              "type":"text"
              , "text":"%L"
              , "links":
              [
                {
                  "filename":"Unknown location"
                  , "line":"0"
                }
              ]
            }
          ]
          , "Dependency: ":"Data dependency"
          , "Estimated fmax reduced to: ":"240.0"
          , "Loop feedback path that lowered II and Fmax: ":
          [
            {
              "type":"text"
              , "text":"f32 FP *+(%L)"
              , "links":
              [
                {
                  "filename":"/home/joerock/Documents/TFM/Quartus_Sim-Em/Squeezenet/device/v1.3/conv3x3/conv3x3_ST.cl"
                  , "line":"43"
                }
              ]
            }
            , {
              "type":"text"
              , "text":"Select(%L)"
              , "links":
              [
                {
                  "filename":"/home/joerock/Documents/TFM/Quartus_Sim-Em/Squeezenet/device/v1.3/conv3x3/conv3x3_ST.cl"
                  , "line":"43"
                }
              ]
            }
          ]
        }
      ]
      , "nodes":
      [
        {
          "name":"Global variable"
          , "id":1953678704
          , "start":"250.00"
          , "parent":"conv2d3x3.B13"
          , "debug":
          [
            [
              {
                "filename":"/home/joerock/Documents/TFM/Quartus_Sim-Em/Squeezenet/device/v1.3/conv3x3/conv3x3_ST.cl"
                , "line":43
              }
            ]
          ]
          , "type":"inst"
        }
        , {
          "name":"f32 FP *+"
          , "id":1953680464
          , "debug":
          [
            [
              {
                "filename":"/home/joerock/Documents/TFM/Quartus_Sim-Em/Squeezenet/device/v1.3/conv3x3/conv3x3_ST.cl"
                , "line":43
              }
            ]
          ]
          , "type":"inst"
        }
        , {
          "name":"Select"
          , "id":1953680816
          , "debug":
          [
            [
              {
                "filename":"/home/joerock/Documents/TFM/Quartus_Sim-Em/Squeezenet/device/v1.3/conv3x3/conv3x3_ST.cl"
                , "line":43
              }
            ]
          ]
          , "type":"inst"
        }
        , {
          "name":"Feedback"
          , "id":1953681168
          , "end":"254.00"
          , "parent":"conv2d3x3.B13"
          , "debug":
          [
            [
              {
                "filename":"/home/joerock/Documents/TFM/Quartus_Sim-Em/Squeezenet/device/v1.3/conv3x3/conv3x3_ST.cl"
                , "line":43
              }
            ]
          ]
          , "type":"inst"
        }
      ]
      , "links":
      [
        {
          "from":1953678704
          , "to":1953680464
        }
        , {
          "from":1953678704
          , "to":1953680816
        }
        , {
          "from":1953680464
          , "to":1953680816
        }
        , {
          "from":1953680816
          , "to":1953681168
        }
        , {
          "from":1953678704
          , "to":1953681168
          , "reverse":1
        }
      ]
    }
    , {
      "name":"Global variable"
      , "id":4294967295
      , "src":"1953403232"
      , "dst":"1953404288"
      , "type":"fMAX/II"
      , "brief":"Data dependency"
      , "loop":"conv2d3x3.B10"
      , "details":
      [
        {
          "type":"table"
          , "Variable on critical loop carried feedback path: ":"Global variable"
          , "Declared at: ":
          [
            {
              "type":"text"
              , "text":"%L"
              , "links":
              [
                {
                  "filename":"Unknown location"
                  , "line":"0"
                }
              ]
            }
          ]
          , "Dependency: ":"Data dependency"
          , "Estimated fmax reduced to: ":"240.0"
          , "Loop feedback path that lowered II and Fmax: ":
          [
            {
              "type":"text"
              , "text":"f32 FP *+(%L)"
              , "links":
              [
                {
                  "filename":"/home/joerock/Documents/TFM/Quartus_Sim-Em/Squeezenet/device/v1.3/conv3x3/conv3x3_ST.cl"
                  , "line":"43"
                }
              ]
            }
            , {
              "type":"text"
              , "text":"Select(%L)"
              , "links":
              [
                {
                  "filename":"/home/joerock/Documents/TFM/Quartus_Sim-Em/Squeezenet/device/v1.3/conv3x3/conv3x3_ST.cl"
                  , "line":"43"
                }
              ]
            }
          ]
        }
      ]
      , "nodes":
      [
        {
          "name":"Global variable"
          , "id":1953403232
          , "start":"253.00"
          , "parent":"conv2d3x3.B10"
          , "debug":
          [
            [
              {
                "filename":"/home/joerock/Documents/TFM/Quartus_Sim-Em/Squeezenet/device/v1.3/conv3x3/conv3x3_ST.cl"
                , "line":43
              }
            ]
          ]
          , "type":"inst"
        }
        , {
          "name":"f32 FP *+"
          , "id":1953403584
          , "debug":
          [
            [
              {
                "filename":"/home/joerock/Documents/TFM/Quartus_Sim-Em/Squeezenet/device/v1.3/conv3x3/conv3x3_ST.cl"
                , "line":43
              }
            ]
          ]
          , "type":"inst"
        }
        , {
          "name":"Select"
          , "id":1953403936
          , "debug":
          [
            [
              {
                "filename":"/home/joerock/Documents/TFM/Quartus_Sim-Em/Squeezenet/device/v1.3/conv3x3/conv3x3_ST.cl"
                , "line":43
              }
            ]
          ]
          , "type":"inst"
        }
        , {
          "name":"Feedback"
          , "id":1953404288
          , "end":"257.00"
          , "parent":"conv2d3x3.B10"
          , "debug":
          [
            [
              {
                "filename":"/home/joerock/Documents/TFM/Quartus_Sim-Em/Squeezenet/device/v1.3/conv3x3/conv3x3_ST.cl"
                , "line":43
              }
            ]
          ]
          , "type":"inst"
        }
      ]
      , "links":
      [
        {
          "from":1953403232
          , "to":1953403584
        }
        , {
          "from":1953403232
          , "to":1953403936
        }
        , {
          "from":1953403584
          , "to":1953403936
        }
        , {
          "from":1953403936
          , "to":1953404288
        }
        , {
          "from":1953403232
          , "to":1953404288
          , "reverse":1
        }
      ]
    }
  ]
}
